{
    "checksum": "74ec4488a9d4aed3b47f8e4d7a58d8bc",
    "wallpaper": "/home/bjtn/.config/wallpapers/flowers_on_the_hill_by_dmitryalexander_dg0ffrp.png",
    "alpha": "100",
    "special": {
        "background": "#16191e",
        "foreground": "#c4c5c6",
        "cursor": "#c4c5c6"
    },
    "colors": {
        "color0": "#16191e",
        "color1": "#A1A1A4",
        "color2": "#CBB7A0",
        "color3": "#E6D2A6",
        "color4": "#9AB5D5",
        "color5": "#B1C7DE",
        "color6": "#E5DED4",
        "color7": "#c4c5c6",
        "color8": "#5e6774",
        "color9": "#A1A1A4",
        "color10": "#CBB7A0",
        "color11": "#E6D2A6",
        "color12": "#9AB5D5",
        "color13": "#B1C7DE",
        "color14": "#E5DED4",
        "color15": "#c4c5c6"
    }
}