{
    "background-color": "#000000",
    "badge-color": "#c6c7c2",
    "bold-color": "#c6c7c2",
    "comment": "",
    "cursor-background-color": "#000000",
    "cursor-foreground-color": "#c6c7c2",
    "foreground-color": "#c6c7c2",
    "highlight-background-color": "#000000",
    "highlight-foreground-color": "#c6c7c2",
    "name": "wal export",
    "palette": [
        "#000000",
        "#696053",
        "#915C39",
        "#8E6C56",
        "#A2926B",
        "#D0AB6B",
        "#5C7583",
        "#c6c7c2",
        "#6b715d",
        "#696053",
        "#915C39",
        "#8E6C56",
        "#A2926B",
        "#D0AB6B",
        "#5C7583",
        "#c6c7c2"
    ],
    "use-badge-color": false,
    "use-bold-color": false,
    "use-cursor-color": false,
    "use-highlight-color": false,
    "use-theme-colors": false
}
